{
  "collectionName": "components_pricing_table_pricing_plans",
  "info": {
    "displayName": "Pricing Plan",
    "description": ""
  },
  "options": {},
  "attributes": {
    "PlanName": {
      "type": "string"
    },
    "PlanUrl": {
      "type": "string"
    },
    "Price": {
      "type": "decimal"
    },
    "RAM": {
      "type": "biginteger"
    },
    "SSD": {
      "type": "biginteger"
    },
    "vCPU": {
      "type": "integer"
    },
    "Traffic": {
      "type": "biginteger"
    },
    "SharedUplink": {
      "type": "string"
    }
  }
}
